varunayan/__init__.py
varunayan/__main__.py
varunayan/cli.py
varunayan/config.py
varunayan/core.py
varunayan/download/__init__.py
varunayan/download/era5_downloader.py
varunayan/processing/__init__.py
varunayan/processing/data_aggregator.py
varunayan/processing/data_filter.py
varunayan/processing/file_handler.py
varunayan/processing/variable_lists.py
varunayan/search_and_desc/__init__.py
varunayan/search_and_desc/pressure_levels_variables.py
varunayan/search_and_desc/search_and_desc_functions.py
varunayan/search_and_desc/single_levels_variables.py
varunayan/util/__init__.py
varunayan/util/geojson_utils.py
varunayan/util/logging_utils.py
varunayan-0.1.1.dist-info/METADATA
varunayan-0.1.1.dist-info/WHEEL
varunayan-0.1.1.dist-info/entry_points.txt
varunayan-0.1.1.dist-info/licenses/LICENSE
varunayan-0.1.1.dist-info/RECORD
